vibe_x/__init__.py
vibe_x/exceptions.py
vibe_x/inline_decoder.py
vibe_x/inline_encoder.py
vibe_x/metablock.py
vibe_x/tokenizer.py
vibex_protocol-1.0.0.dist-info/licenses/LICENSE
vibex_protocol-1.0.0.dist-info/METADATA
vibex_protocol-1.0.0.dist-info/WHEEL
vibex_protocol-1.0.0.dist-info/top_level.txt
vibex_protocol-1.0.0.dist-info/RECORD
