Metadata-Version: 2.4
Name: vibex-protocol
Version: 1.0.0
Summary: VIBE-X Protocol: Vector-Integrated Binary Extension for emotional and contextual metadata encoding.
Author: Uğur Kandemiş
License: MIT
Project-URL: Homepage, https://github.com/vibexcode/vibe-x-protocol
Project-URL: Documentation, https://github.com/vibexcode/vibe-x-protocol
Project-URL: Source, https://github.com/vibexcode/vibe-x-protocol
Project-URL: Issues, https://github.com/vibexcode/vibe-x-protocol/issues
Keywords: sentiment-analysis,metadata,affective-computing,nlp,text-encoding,protocol
Classifier: Programming Language :: Python :: 3
Classifier: License :: OSI Approved :: MIT License
Classifier: Operating System :: OS Independent
Classifier: Intended Audience :: Science/Research
Classifier: Topic :: Scientific/Engineering :: Artificial Intelligence
Requires-Python: >=3.10
License-File: LICENSE
Dynamic: license-file
